CHANGES.rst
CONTRIBUTORS.rst
DEVELOP.rst
LICENSE.rst
MANIFEST.in
README.rst
setup.cfg
setup.py
docs/index.rst
src/c2/__init__.py
src/c2.patch.plone4year2021.egg-info/PKG-INFO
src/c2.patch.plone4year2021.egg-info/SOURCES.txt
src/c2.patch.plone4year2021.egg-info/dependency_links.txt
src/c2.patch.plone4year2021.egg-info/entry_points.txt
src/c2.patch.plone4year2021.egg-info/namespace_packages.txt
src/c2.patch.plone4year2021.egg-info/not-zip-safe
src/c2.patch.plone4year2021.egg-info/requires.txt
src/c2.patch.plone4year2021.egg-info/top_level.txt
src/c2/patch/__init__.py
src/c2/patch/plone4year2021/__init__.py
src/c2/patch/plone4year2021/configure.zcml
src/c2/patch/plone4year2021/monkey.py
src/c2/patch/plone4year2021/testing.py
src/c2/patch/plone4year2021/tests/__init__.py