Metadata-Version: 1.1
Name: c2.patch.plone4year2021
Version: 1.0a2
Summary: This product is monkey patching selected year problem after 2021 for Plone 4
Home-page: https://pypi.python.org/pypi/c2.patch.plone4year2021
Author: Manabu TERADA
Author-email: terada@cmscom.jp
License: GPL version 2
Keywords: Python Plone
Platform: UNKNOWN
Classifier: Environment :: Web Environment
Classifier: Framework :: Plone
Classifier: Framework :: Plone :: 4.0
Classifier: Framework :: Plone :: 4.1
Classifier: Framework :: Plone :: 4.2
Classifier: Framework :: Plone :: 4.3
Classifier: Programming Language :: Python
Classifier: Programming Language :: Python :: 2.7
Classifier: Operating System :: OS Independent
Classifier: License :: OSI Approved :: GNU General Public License v2 (GPLv2)
